EEG_P300_Waveform_FSM/Scripts/eeg_fsm_p300.v
module eeg_fsm_p300 (
    input clk,                 // Clock signal
    input reset,               // Reset signal
    input [7:0] eeg_signal,    // 8-bit EEG input signal
    output reg detected        // Output: P300 pattern detected or not
);
    // state Encoding
    parameter IDLE = 3'b000;
    parameter RISING = 3'b001;
    parameter PEAK = 3'b010;
    parameter FALLING = 3'b011;
    parameter DETECTED = 3'b100;

    reg [2:0] current_state, next_state;

    // Thresholds
    reg [7:0] baseline = 8'd50;         // Baseline signal value (calibrated value in reality.)
    reg [7:0] rise_threshold = 8'd70;   // Min peak amplitude
    reg [7:0] fall_threshold = 8'd60;   // decay

    // Counter for timeout during p300 detection
    reg [9:0] counter;

    // FSM Sequential Logic
    always @(posedge clk or posedge reset) begin
        // RESET = IDLE state
        if (reset) begin
            current_state <= IDLE;
            counter <= 0;
            detected <= 0;
        end 
        else begin
            current_state <= next_state;
            // Update counter based on state
            if (current_state == RISING || current_state == PEAK) begin
                counter <= counter + 1;
            end else begin
                counter <= 0; // Reset counter for other states
            end
        end
    end

    // FSM Combinational Logic
    always @(*) begin
        case (current_state)
            IDLE: begin
                // Move to RISING state
                if (eeg_signal > baseline)
                    next_state = RISING;
            end
            RISING: begin
                // CASE: Timeout
                if (counter >= 300) begin
                    next_state = IDLE;
                end
                // Move to PEAK state 
                else if (eeg_signal > rise_threshold) begin
                    next_state = PEAK;
                end
                 // CASE: False start
                else if (eeg_signal <= baseline) begin
                    next_state = IDLE;        
                end
            end
            PEAK: begin
                // CASE: Timeout
                if (counter >= 300) begin
                    next_state = IDLE;        
                end
                // Move to FALLING state
                else if (eeg_signal <= fall_threshold) begin
                    next_state = FALLING;
                end
                 // CASE: False pattern
                else if (eeg_signal < rise_threshold) begin
                    next_state = IDLE;     
                end
            end
            FALLING: begin
                // Move to Pattern Detected state
                if (eeg_signal <= baseline)
                    next_state = DETECTED;
            end
            DETECTED: begin
                // P300 pattern detected
                detected = 1;               
            end
            default: begin
                next_state = IDLE;  // Reset FSM by default or any Invalid transition
                detected = 0;       // Set to LOW in next cycle after its HIGH OR by Default.
            end
        endcase
    end
endmodule

EEG_P300_Waveform_FSM/Scripts/eeg_fsm_p300_TB.v
module testbench;
    reg clk;                  
    reg reset;                
    reg [7:0] eeg_signal;     
    wire detected;

    eeg_fsm_p300 uut (
        .clk(clk),
        .reset(reset),
        .eeg_signal(eeg_signal),
        .detected(detected)
    );

    always begin
        #1 clk = ~clk; // #1 for half-period
    end

    // Test cases --------------
    initial begin
        clk = 0;
        reset = 1;
        eeg_signal = 8'd50;
        #10 reset = 0;      // reset after some time

        $display("Test Case 1: Timeout scenario");
        #10 eeg_signal = 8'd55; // Rising phase
        #550 eeg_signal = 8'd75; // Peak occurs too late
        #20 eeg_signal = 8'd65;  // Falling phase
        #20 eeg_signal = 8'd51;  // Back to baseline
        #20 if (!detected) $display("P300 Timeout: PASS");
            else $display("P300 Timeout: FAIL");

        $display("Test Case 2: False positive prevention");
        #20 eeg_signal = 8'd55; // Rising
        #20 eeg_signal = 8'd60; // No actual peak (threshold not met)
        #20 eeg_signal = 8'd50; // Back to baseline
        #20 if (!detected) $display("No False Positive: PASS");
            else $display("No False Positive: FAIL");

        $display("Test Case 3: Valid P300 pattern");
        #20 eeg_signal = 8'd55; // Rising phase
        #20 eeg_signal = 8'd75; // Peak phase
        #20 eeg_signal = 8'd59; // Falling phase
        #20 eeg_signal = 8'd50; // Back to baseline
        #20 if (detected) $display("P300 Detected: PASS");
            else $display("P300 Detected: FAIL");

        #50 $finish;
    end

    // Dump waveforms for simulation (VCD)
    initial begin
        $dumpfile("eeg_fsm_p300.vcd");
        $dumpvars(0, testbench);
    end

endmodule

EEG_P300_Waveform_FSM/Scripts/eeg_fsm_p300.vcd
$date
	Mon Nov 25 14:44:29 2024
$end
$version
	Icarus Verilog
$end
$timescale
	1s
$end
$scope module testbench $end
$var wire 1 ! detected $end
$var reg 1 " clk $end
$var reg 8 # eeg_signal [7:0] $end
$var reg 1 $ reset $end
$scope module uut $end
$var wire 1 " clk $end
$var wire 8 % eeg_signal [7:0] $end
$var wire 1 $ reset $end
$var parameter 3 & DETECTED $end
$var parameter 3 ' FALLING $end
$var parameter 3 ( IDLE $end
$var parameter 3 ) PEAK $end
$var parameter 3 * RISING $end
$var reg 8 + baseline [7:0] $end
$var reg 10 , counter [9:0] $end
$var reg 3 - current_state [2:0] $end
$var reg 1 ! detected $end
$var reg 8 . fall_threshold [7:0] $end
$var reg 3 / next_state [2:0] $end
$var reg 8 0 rise_threshold [7:0] $end
$upscope $end
$upscope $end
$enddefinitions $end
$comment Show the parameter values. $end
$dumpall
b1 *
b10 )
b0 (
b11 '
b100 &
$end
#0
$dumpvars
b1000110 0
b0 /
b111100 .
b0 -
b0 ,
b110010 +
b110010 %
1$
b110010 #
0"
0!
$end
#1
1"
#2
0"
#3
1"
#4
0"
#5
1"
#6
0"
#7
1"
#8
0"
#9
1"
#10
0"
0$
#11
1"
#12
0"
#13
1"
#14
0"
#15
1"
#16
0"
#17
1"
#18
0"
#19
1"
#20
b1 /
0"
b110111 #
b110111 %
#21
b1 -
1"
#22
0"
#23
b1 ,
1"
#24
0"
#25
b10 ,
1"
#26
0"
#27
b11 ,
1"
#28
0"
#29
b100 ,
1"
#30
0"
#31
b101 ,
1"
#32
0"
#33
b110 ,
1"
#34
0"
#35
b111 ,
1"
#36
0"
#37
b1000 ,
1"
#38
0"
#39
b1001 ,
1"
#40
0"
#41
b1010 ,
1"
#42
0"
#43
b1011 ,
1"
#44
0"
#45
b1100 ,
1"
#46
0"
#47
b1101 ,
1"
#48
0"
#49
b1110 ,
1"
#50
0"
#51
b1111 ,
1"
#52
0"
#53
b10000 ,
1"
#54
0"
#55
b10001 ,
1"
#56
0"
#57
b10010 ,
1"
#58
0"
#59
b10011 ,
1"
#60
0"
#61
b10100 ,
1"
#62
0"
#63
b10101 ,
1"
#64
0"
#65
b10110 ,
1"
#66
0"
#67
b10111 ,
1"
#68
0"
#69
b11000 ,
1"
#70
0"
#71
b11001 ,
1"
#72
0"
#73
b11010 ,
1"
#74
0"
#75
b11011 ,
1"
#76
0"
#77
b11100 ,
1"
#78
0"
#79
b11101 ,
1"
#80
0"
#81
b11110 ,
1"
#82
0"
#83
b11111 ,
1"
#84
0"
#85
b100000 ,
1"
#86
0"
#87
b100001 ,
1"
#88
0"
#89
b100010 ,
1"
#90
0"
#91
b100011 ,
1"
#92
0"
#93
b100100 ,
1"
#94
0"
#95
b100101 ,
1"
#96
0"
#97
b100110 ,
1"
#98
0"
#99
b100111 ,
1"
#100
0"
#101
b101000 ,
1"
#102
0"
#103
b101001 ,
1"
#104
0"
#105
b101010 ,
1"
#106
0"
#107
b101011 ,
1"
#108
0"
#109
b101100 ,
1"
#110
0"
#111
b101101 ,
1"
#112
0"
#113
b101110 ,
1"
#114
0"
#115
b101111 ,
1"
#116
0"
#117
b110000 ,
1"
#118
0"
#119
b110001 ,
1"
#120
0"
#121
b110010 ,
1"
#122
0"
#123
b110011 ,
1"
#124
0"
#125
b110100 ,
1"
#126
0"
#127
b110101 ,
1"
#128
0"
#129
b110110 ,
1"
#130
0"
#131
b110111 ,
1"
#132
0"
#133
b111000 ,
1"
#134
0"
#135
b111001 ,
1"
#136
0"
#137
b111010 ,
1"
#138
0"
#139
b111011 ,
1"
#140
0"
#141
b111100 ,
1"
#142
0"
#143
b111101 ,
1"
#144
0"
#145
b111110 ,
1"
#146
0"
#147
b111111 ,
1"
#148
0"
#149
b1000000 ,
1"
#150
0"
#151
b1000001 ,
1"
#152
0"
#153
b1000010 ,
1"
#154
0"
#155
b1000011 ,
1"
#156
0"
#157
b1000100 ,
1"
#158
0"
#159
b1000101 ,
1"
#160
0"
#161
b1000110 ,
1"
#162
0"
#163
b1000111 ,
1"
#164
0"
#165
b1001000 ,
1"
#166
0"
#167
b1001001 ,
1"
#168
0"
#169
b1001010 ,
1"
#170
0"
#171
b1001011 ,
1"
#172
0"
#173
b1001100 ,
1"
#174
0"
#175
b1001101 ,
1"
#176
0"
#177
b1001110 ,
1"
#178
0"
#179
b1001111 ,
1"
#180
0"
#181
b1010000 ,
1"
#182
0"
#183
b1010001 ,
1"
#184
0"
#185
b1010010 ,
1"
#186
0"
#187
b1010011 ,
1"
#188
0"
#189
b1010100 ,
1"
#190
0"
#191
b1010101 ,
1"
#192
0"
#193
b1010110 ,
1"
#194
0"
#195
b1010111 ,
1"
#196
0"
#197
b1011000 ,
1"
#198
0"
#199
b1011001 ,
1"
#200
0"
#201
b1011010 ,
1"
#202
0"
#203
b1011011 ,
1"
#204
0"
#205
b1011100 ,
1"
#206
0"
#207
b1011101 ,
1"
#208
0"
#209
b1011110 ,
1"
#210
0"
#211
b1011111 ,
1"
#212
0"
#213
b1100000 ,
1"
#214
0"
#215
b1100001 ,
1"
#216
0"
#217
b1100010 ,
1"
#218
0"
#219
b1100011 ,
1"
#220
0"
#221
b1100100 ,
1"
#222
0"
#223
b1100101 ,
1"
#224
0"
#225
b1100110 ,
1"
#226
0"
#227
b1100111 ,
1"
#228
0"
#229
b1101000 ,
1"
#230
0"
#231
b1101001 ,
1"
#232
0"
#233
b1101010 ,
1"
#234
0"
#235
b1101011 ,
1"
#236
0"
#237
b1101100 ,
1"
#238
0"
#239
b1101101 ,
1"
#240
0"
#241
b1101110 ,
1"
#242
0"
#243
b1101111 ,
1"
#244
0"
#245
b1110000 ,
1"
#246
0"
#247
b1110001 ,
1"
#248
0"
#249
b1110010 ,
1"
#250
0"
#251
b1110011 ,
1"
#252
0"
#253
b1110100 ,
1"
#254
0"
#255
b1110101 ,
1"
#256
0"
#257
b1110110 ,
1"
#258
0"
#259
b1110111 ,
1"
#260
0"
#261
b1111000 ,
1"
#262
0"
#263
b1111001 ,
1"
#264
0"
#265
b1111010 ,
1"
#266
0"
#267
b1111011 ,
1"
#268
0"
#269
b1111100 ,
1"
#270
0"
#271
b1111101 ,
1"
#272
0"
#273
b1111110 ,
1"
#274
0"
#275
b1111111 ,
1"
#276
0"
#277
b10000000 ,
1"
#278
0"
#279
b10000001 ,
1"
#280
0"
#281
b10000010 ,
1"
#282
0"
#283
b10000011 ,
1"
#284
0"
#285
b10000100 ,
1"
#286
0"
#287
b10000101 ,
1"
#288
0"
#289
b10000110 ,
1"
#290
0"
#291
b10000111 ,
1"
#292
0"
#293
b10001000 ,
1"
#294
0"
#295
b10001001 ,
1"
#296
0"
#297
b10001010 ,
1"
#298
0"
#299
b10001011 ,
1"
#300
0"
#301
b10001100 ,
1"
#302
0"
#303
b10001101 ,
1"
#304
0"
#305
b10001110 ,
1"
#306
0"
#307
b10001111 ,
1"
#308
0"
#309
b10010000 ,
1"
#310
0"
#311
b10010001 ,
1"
#312
0"
#313
b10010010 ,
1"
#314
0"
#315
b10010011 ,
1"
#316
0"
#317
b10010100 ,
1"
#318
0"
#319
b10010101 ,
1"
#320
0"
#321
b10010110 ,
1"
#322
0"
#323
b10010111 ,
1"
#324
0"
#325
b10011000 ,
1"
#326
0"
#327
b10011001 ,
1"
#328
0"
#329
b10011010 ,
1"
#330
0"
#331
b10011011 ,
1"
#332
0"
#333
b10011100 ,
1"
#334
0"
#335
b10011101 ,
1"
#336
0"
#337
b10011110 ,
1"
#338
0"
#339
b10011111 ,
1"
#340
0"
#341
b10100000 ,
1"
#342
0"
#343
b10100001 ,
1"
#344
0"
#345
b10100010 ,
1"
#346
0"
#347
b10100011 ,
1"
#348
0"
#349
b10100100 ,
1"
#350
0"
#351
b10100101 ,
1"
#352
0"
#353
b10100110 ,
1"
#354
0"
#355
b10100111 ,
1"
#356
0"
#357
b10101000 ,
1"
#358
0"
#359
b10101001 ,
1"
#360
0"
#361
b10101010 ,
1"
#362
0"
#363
b10101011 ,
1"
#364
0"
#365
b10101100 ,
1"
#366
0"
#367
b10101101 ,
1"
#368
0"
#369
b10101110 ,
1"
#370
0"
#371
b10101111 ,
1"
#372
0"
#373
b10110000 ,
1"
#374
0"
#375
b10110001 ,
1"
#376
0"
#377
b10110010 ,
1"
#378
0"
#379
b10110011 ,
1"
#380
0"
#381
b10110100 ,
1"
#382
0"
#383
b10110101 ,
1"
#384
0"
#385
b10110110 ,
1"
#386
0"
#387
b10110111 ,
1"
#388
0"
#389
b10111000 ,
1"
#390
0"
#391
b10111001 ,
1"
#392
0"
#393
b10111010 ,
1"
#394
0"
#395
b10111011 ,
1"
#396
0"
#397
b10111100 ,
1"
#398
0"
#399
b10111101 ,
1"
#400
0"
#401
b10111110 ,
1"
#402
0"
#403
b10111111 ,
1"
#404
0"
#405
b11000000 ,
1"
#406
0"
#407
b11000001 ,
1"
#408
0"
#409
b11000010 ,
1"
#410
0"
#411
b11000011 ,
1"
#412
0"
#413
b11000100 ,
1"
#414
0"
#415
b11000101 ,
1"
#416
0"
#417
b11000110 ,
1"
#418
0"
#419
b11000111 ,
1"
#420
0"
#421
b11001000 ,
1"
#422
0"
#423
b11001001 ,
1"
#424
0"
#425
b11001010 ,
1"
#426
0"
#427
b11001011 ,
1"
#428
0"
#429
b11001100 ,
1"
#430
0"
#431
b11001101 ,
1"
#432
0"
#433
b11001110 ,
1"
#434
0"
#435
b11001111 ,
1"
#436
0"
#437
b11010000 ,
1"
#438
0"
#439
b11010001 ,
1"
#440
0"
#441
b11010010 ,
1"
#442
0"
#443
b11010011 ,
1"
#444
0"
#445
b11010100 ,
1"
#446
0"
#447
b11010101 ,
1"
#448
0"
#449
b11010110 ,
1"
#450
0"
#451
b11010111 ,
1"
#452
0"
#453
b11011000 ,
1"
#454
0"
#455
b11011001 ,
1"
#456
0"
#457
b11011010 ,
1"
#458
0"
#459
b11011011 ,
1"
#460
0"
#461
b11011100 ,
1"
#462
0"
#463
b11011101 ,
1"
#464
0"
#465
b11011110 ,
1"
#466
0"
#467
b11011111 ,
1"
#468
0"
#469
b11100000 ,
1"
#470
0"
#471
b11100001 ,
1"
#472
0"
#473
b11100010 ,
1"
#474
0"
#475
b11100011 ,
1"
#476
0"
#477
b11100100 ,
1"
#478
0"
#479
b11100101 ,
1"
#480
0"
#481
b11100110 ,
1"
#482
0"
#483
b11100111 ,
1"
#484
0"
#485
b11101000 ,
1"
#486
0"
#487
b11101001 ,
1"
#488
0"
#489
b11101010 ,
1"
#490
0"
#491
b11101011 ,
1"
#492
0"
#493
b11101100 ,
1"
#494
0"
#495
b11101101 ,
1"
#496
0"
#497
b11101110 ,
1"
#498
0"
#499
b11101111 ,
1"
#500
0"
#501
b11110000 ,
1"
#502
0"
#503
b11110001 ,
1"
#504
0"
#505
b11110010 ,
1"
#506
0"
#507
b11110011 ,
1"
#508
0"
#509
b11110100 ,
1"
#510
0"
#511
b11110101 ,
1"
#512
0"
#513
b11110110 ,
1"
#514
0"
#515
b11110111 ,
1"
#516
0"
#517
b11111000 ,
1"
#518
0"
#519
b11111001 ,
1"
#520
0"
#521
b11111010 ,
1"
#522
0"
#523
b11111011 ,
1"
#524
0"
#525
b11111100 ,
1"
#526
0"
#527
b11111101 ,
1"
#528
0"
#529
b11111110 ,
1"
#530
0"
#531
b11111111 ,
1"
#532
0"
#533
b100000000 ,
1"
#534
0"
#535
b100000001 ,
1"
#536
0"
#537
b100000010 ,
1"
#538
0"
#539
b100000011 ,
1"
#540
0"
#541
b100000100 ,
1"
#542
0"
#543
b100000101 ,
1"
#544
0"
#545
b100000110 ,
1"
#546
0"
#547
b100000111 ,
1"
#548
0"
#549
b100001000 ,
1"
#550
0"
#551
b100001001 ,
1"
#552
0"
#553
b100001010 ,
1"
#554
0"
#555
b100001011 ,
1"
#556
0"
#557
b100001100 ,
1"
#558
0"
#559
b100001101 ,
1"
#560
0"
#561
b100001110 ,
1"
#562
0"
#563
b100001111 ,
1"
#564
0"
#565
b100010000 ,
1"
#566
0"
#567
b100010001 ,
1"
#568
0"
#569
b100010010 ,
1"
#570
b10 /
0"
b1001011 #
b1001011 %
#571
b100010011 ,
b10 -
1"
#572
0"
#573
b100010100 ,
1"
#574
0"
#575
b100010101 ,
1"
#576
0"
#577
b100010110 ,
1"
#578
0"
#579
b100010111 ,
1"
#580
0"
#581
b100011000 ,
1"
#582
0"
#583
b100011001 ,
1"
#584
0"
#585
b100011010 ,
1"
#586
0"
#587
b100011011 ,
1"
#588
0"
#589
b100011100 ,
1"
#590
b0 /
0"
b1000001 #
b1000001 %
#591
b1 /
b100011101 ,
b0 -
1"
#592
0"
#593
b0 ,
b1 -
1"
#594
0"
#595
b1 ,
1"
#596
0"
#597
b10 ,
1"
#598
0"
#599
b11 ,
1"
#600
0"
#601
b100 ,
1"
#602
0"
#603
b101 ,
1"
#604
0"
#605
b110 ,
1"
#606
0"
#607
b111 ,
1"
#608
0"
#609
b1000 ,
1"
#610
0"
b110011 #
b110011 %
#611
b1001 ,
1"
#612
0"
#613
b1010 ,
1"
#614
0"
#615
b1011 ,
1"
#616
0"
#617
b1100 ,
1"
#618
0"
#619
b1101 ,
1"
#620
0"
#621
b1110 ,
1"
#622
0"
#623
b1111 ,
1"
#624
0"
#625
b10000 ,
1"
#626
0"
#627
b10001 ,
1"
#628
0"
#629
b10010 ,
1"
#630
0"
#631
b10011 ,
1"
#632
0"
#633
b10100 ,
1"
#634
0"
#635
b10101 ,
1"
#636
0"
#637
b10110 ,
1"
#638
0"
#639
b10111 ,
1"
#640
0"
#641
b11000 ,
1"
#642
0"
#643
b11001 ,
1"
#644
0"
#645
b11010 ,
1"
#646
0"
#647
b11011 ,
1"
#648
0"
#649
b11100 ,
1"
#650
0"
b110111 #
b110111 %
#651
b11101 ,
1"
#652
0"
#653
b11110 ,
1"
#654
0"
#655
b11111 ,
1"
#656
0"
#657
b100000 ,
1"
#658
0"
#659
b100001 ,
1"
#660
0"
#661
b100010 ,
1"
#662
0"
#663
b100011 ,
1"
#664
0"
#665
b100100 ,
1"
#666
0"
#667
b100101 ,
1"
#668
0"
#669
b100110 ,
1"
#670
0"
b111100 #
b111100 %
#671
b100111 ,
1"
#672
0"
#673
b101000 ,
1"
#674
0"
#675
b101001 ,
1"
#676
0"
#677
b101010 ,
1"
#678
0"
#679
b101011 ,
1"
#680
0"
#681
b101100 ,
1"
#682
0"
#683
b101101 ,
1"
#684
0"
#685
b101110 ,
1"
#686
0"
#687
b101111 ,
1"
#688
0"
#689
b110000 ,
1"
#690
b0 /
0"
b110010 #
b110010 %
#691
b110001 ,
b0 -
1"
#692
0"
#693
b0 ,
1"
#694
0"
#695
1"
#696
0"
#697
1"
#698
0"
#699
1"
#700
0"
#701
1"
#702
0"
#703
1"
#704
0"
#705
1"
#706
0"
#707
1"
#708
0"
#709
1"
#710
0"
#711
1"
#712
0"
#713
1"
#714
0"
#715
1"
#716
0"
#717
1"
#718
0"
#719
1"
#720
0"
#721
1"
#722
0"
#723
1"
#724
0"
#725
1"
#726
0"
#727
1"
#728
0"
#729
1"
#730
b1 /
0"
b110111 #
b110111 %
#731
b1 -
1"
#732
0"
#733
b1 ,
1"
#734
0"
#735
b10 ,
1"
#736
0"
#737
b11 ,
1"
#738
0"
#739
b100 ,
1"
#740
0"
#741
b101 ,
1"
#742
0"
#743
b110 ,
1"
#744
0"
#745
b111 ,
1"
#746
0"
#747
b1000 ,
1"
#748
0"
#749
b1001 ,
1"
#750
b10 /
0"
b1001011 #
b1001011 %
#751
b1010 ,
b10 -
1"
#752
0"
#753
b1011 ,
1"
#754
0"
#755
b1100 ,
1"
#756
0"
#757
b1101 ,
1"
#758
0"
#759
b1110 ,
1"
#760
0"
#761
b1111 ,
1"
#762
0"
#763
b10000 ,
1"
#764
0"
#765
b10001 ,
1"
#766
0"
#767
b10010 ,
1"
#768
0"
#769
b10011 ,
1"
#770
b11 /
0"
b111011 #
b111011 %
#771
b10100 ,
b11 -
1"
#772
0"
#773
b0 ,
1"
#774
0"
#775
1"
#776
0"
#777
1"
#778
0"
#779
1"
#780
0"
#781
1"
#782
0"
#783
1"
#784
0"
#785
1"
#786
0"
#787
1"
#788
0"
#789
1"
#790
b100 /
0"
b110010 #
b110010 %
#791
1!
b100 -
1"
